lexios/__init__.py
lexios/error.py
lexios/matter.py
lexios/system.py
lexios/typing.py
lexios/unit.py
lexios/universe.py
lexios/utils.py
lexios/version.py
lexios-0.0.1.dist-info/LICENSE
lexios-0.0.1.dist-info/METADATA
lexios-0.0.1.dist-info/WHEEL
lexios-0.0.1.dist-info/top_level.txt
lexios-0.0.1.dist-info/RECORD
